SSHLitebrary-0.1.1.dist-info/METADATA
SSHLitebrary-0.1.1.dist-info/RECORD
SSHLitebrary-0.1.1.dist-info/WHEEL
SSHLitebrary-0.1.1.dist-info/top_level.txt
sshlitebrary/__init__.py
sshlitebrary/abstractclient.py
sshlitebrary/config.py
sshlitebrary/library.py
sshlitebrary/pythonclient.py
sshlitebrary/utils/__init__.py
sshlitebrary/utils/connectioncache.py
sshlitebrary/utils/misc.py
sshlitebrary/utils/normalizing.py
sshlitebrary/utils/robottime.py
sshlitebrary/utils/robottypes.py
sshlitebrary/utils/unic.py
